{
  "venues": [
    {
      "venueId": "metlife",
      "name": "MetLife Stadium",
      "city": "East Rutherford",
      "state": "New Jersey",
      "country": "USA",
      "capacity": 82500,
      "latitude": 40.8128,
      "longitude": -74.0742,
      "timeZone": "America/New_York",
      "imageUrl": "assets/worldcup/stadiums/metlife_stadium.jpg",
      "address": "1 MetLife Stadium Dr, East Rutherford, NJ 07073",
      "significance": "FINAL VENUE",
      "matchesHosted": 8,
      "description": "Home to the New York Giants and Jets. Will host the FIFA World Cup 2026 Final on July 19, 2026."
    },
    {
      "venueId": "att",
      "name": "AT&T Stadium",
      "city": "Arlington",
      "state": "Texas",
      "country": "USA",
      "capacity": 80000,
      "latitude": 32.7473,
      "longitude": -97.0945,
      "timeZone": "America/Chicago",
      "imageUrl": "assets/worldcup/stadiums/att_stadium.jpg",
      "address": "1 AT&T Way, Arlington, TX 76011",
      "significance": "SEMI-FINAL VENUE",
      "matchesHosted": 9,
      "description": "Home of the Dallas Cowboys. Features the world's largest HD video screen. Semi-final venue."
    },
    {
      "venueId": "mercedes_benz_atlanta",
      "name": "Mercedes-Benz Stadium",
      "city": "Atlanta",
      "state": "Georgia",
      "country": "USA",
      "capacity": 71000,
      "latitude": 33.7554,
      "longitude": -84.4008,
      "timeZone": "America/New_York",
      "imageUrl": "assets/worldcup/stadiums/mercedes_benz_atlanta.jpg",
      "address": "1 AMB Dr NW, Atlanta, GA 30313",
      "significance": "SEMI-FINAL VENUE",
      "matchesHosted": 8,
      "description": "Home of the Atlanta Falcons. Features a retractable roof with unique petal design. Semi-final venue."
    },
    {
      "venueId": "sofi",
      "name": "SoFi Stadium",
      "city": "Inglewood",
      "state": "California",
      "country": "USA",
      "capacity": 70000,
      "latitude": 33.9535,
      "longitude": -118.3392,
      "timeZone": "America/Los_Angeles",
      "imageUrl": "assets/worldcup/stadiums/sofi_stadium.jpg",
      "address": "1001 S Stadium Dr, Inglewood, CA 90301",
      "significance": "Opening Match USA",
      "matchesHosted": 8,
      "description": "State-of-the-art stadium opened in 2020. Home of LA Rams and Chargers."
    },
    {
      "venueId": "hard_rock",
      "name": "Hard Rock Stadium",
      "city": "Miami Gardens",
      "state": "Florida",
      "country": "USA",
      "capacity": 65000,
      "latitude": 25.9580,
      "longitude": -80.2389,
      "timeZone": "America/New_York",
      "imageUrl": "assets/worldcup/stadiums/hard_rock_stadium.jpg",
      "address": "347 Don Shula Dr, Miami Gardens, FL 33056",
      "significance": "Third Place Match",
      "matchesHosted": 7,
      "description": "Home of the Miami Dolphins. Will host the Third Place playoff match."
    },
    {
      "venueId": "nrg",
      "name": "NRG Stadium",
      "city": "Houston",
      "state": "Texas",
      "country": "USA",
      "capacity": 72000,
      "latitude": 29.6847,
      "longitude": -95.4107,
      "timeZone": "America/Chicago",
      "imageUrl": "assets/worldcup/stadiums/nrg_stadium.jpg",
      "address": "NRG Pkwy, Houston, TX 77054",
      "significance": "Quarter-Final Venue",
      "matchesHosted": 7,
      "description": "Home of the Houston Texans. Features a retractable roof."
    },
    {
      "venueId": "lincoln_financial",
      "name": "Lincoln Financial Field",
      "city": "Philadelphia",
      "state": "Pennsylvania",
      "country": "USA",
      "capacity": 69000,
      "latitude": 39.9008,
      "longitude": -75.1675,
      "timeZone": "America/New_York",
      "imageUrl": "assets/worldcup/stadiums/lincoln_financial_field.jpg",
      "address": "1020 Pattison Ave, Philadelphia, PA 19148",
      "significance": "Round of 32 Venue",
      "matchesHosted": 6,
      "description": "Home of the Philadelphia Eagles."
    },
    {
      "venueId": "lumen",
      "name": "Lumen Field",
      "city": "Seattle",
      "state": "Washington",
      "country": "USA",
      "capacity": 69000,
      "latitude": 47.5952,
      "longitude": -122.3316,
      "timeZone": "America/Los_Angeles",
      "imageUrl": "assets/worldcup/stadiums/lumen_field.jpg",
      "address": "800 Occidental Ave S, Seattle, WA 98134",
      "significance": "Group Stage",
      "matchesHosted": 6,
      "description": "Home of the Seattle Seahawks and Sounders FC."
    },
    {
      "venueId": "levis",
      "name": "Levi's Stadium",
      "city": "Santa Clara",
      "state": "California",
      "country": "USA",
      "capacity": 68500,
      "latitude": 37.4032,
      "longitude": -121.9698,
      "timeZone": "America/Los_Angeles",
      "imageUrl": "assets/worldcup/stadiums/levis_stadium.jpg",
      "address": "4900 Marie P DeBartolo Way, Santa Clara, CA 95054",
      "significance": "Round of 16 Venue",
      "matchesHosted": 6,
      "description": "Home of the San Francisco 49ers."
    },
    {
      "venueId": "gillette",
      "name": "Gillette Stadium",
      "city": "Foxborough",
      "state": "Massachusetts",
      "country": "USA",
      "capacity": 65000,
      "latitude": 42.0909,
      "longitude": -71.2643,
      "timeZone": "America/New_York",
      "imageUrl": "assets/worldcup/stadiums/gillette_stadium.jpg",
      "address": "1 Patriot Pl, Foxborough, MA 02035",
      "significance": "Group Stage",
      "matchesHosted": 5,
      "description": "Home of the New England Patriots and Revolution."
    },
    {
      "venueId": "arrowhead",
      "name": "GEHA Field at Arrowhead Stadium",
      "city": "Kansas City",
      "state": "Missouri",
      "country": "USA",
      "capacity": 76000,
      "latitude": 39.0489,
      "longitude": -94.4839,
      "timeZone": "America/Chicago",
      "imageUrl": "assets/worldcup/stadiums/arrowhead_stadium.jpg",
      "address": "1 Arrowhead Dr, Kansas City, MO 64129",
      "significance": "Group Stage",
      "matchesHosted": 6,
      "description": "Home of the Kansas City Chiefs. Known for the loudest stadium crowd."
    },
    {
      "venueId": "azteca",
      "name": "Estadio Azteca",
      "city": "Mexico City",
      "state": "CDMX",
      "country": "Mexico",
      "capacity": 87000,
      "latitude": 19.3029,
      "longitude": -99.1506,
      "timeZone": "America/Mexico_City",
      "imageUrl": "assets/worldcup/stadiums/estadio_azteca.jpg",
      "address": "Calz. de Tlalpan 3465, Sta. Úrsula Coapa, Mexico City",
      "significance": "OPENING MATCH",
      "matchesHosted": 9,
      "description": "Iconic stadium that hosted 1970 and 1986 World Cup Finals. Opening match venue for 2026."
    },
    {
      "venueId": "akron",
      "name": "Estadio Akron",
      "city": "Guadalajara",
      "state": "Jalisco",
      "country": "Mexico",
      "capacity": 49850,
      "latitude": 20.6934,
      "longitude": -103.4633,
      "timeZone": "America/Mexico_City",
      "imageUrl": "assets/worldcup/stadiums/estadio_akron.jpg",
      "address": "Av. Akron S/N, Zapopan, Jalisco",
      "significance": "Group Stage",
      "matchesHosted": 5,
      "description": "Home of Chivas de Guadalajara. Modern stadium opened in 2010."
    },
    {
      "venueId": "bbva",
      "name": "Estadio BBVA",
      "city": "Monterrey",
      "state": "Nuevo León",
      "country": "Mexico",
      "capacity": 53500,
      "latitude": 25.7209,
      "longitude": -100.2877,
      "timeZone": "America/Monterrey",
      "imageUrl": "assets/worldcup/stadiums/estadio_bbva.jpg",
      "address": "Av. Pablo Livas 2011, Guadalupe, N.L.",
      "significance": "Round of 32 Venue",
      "matchesHosted": 6,
      "description": "Home of CF Monterrey. Opened in 2015 with modern facilities."
    },
    {
      "venueId": "bmo",
      "name": "BMO Field",
      "city": "Toronto",
      "state": "Ontario",
      "country": "Canada",
      "capacity": 45500,
      "latitude": 43.6333,
      "longitude": -79.4186,
      "timeZone": "America/Toronto",
      "imageUrl": "assets/worldcup/stadiums/bmo_field.jpg",
      "address": "170 Princes' Blvd, Toronto, ON M6K 3C3",
      "significance": "Canada Opening Match",
      "matchesHosted": 6,
      "description": "Home of Toronto FC. Will host Canada's opening match on June 12, 2026."
    },
    {
      "venueId": "bc_place",
      "name": "BC Place",
      "city": "Vancouver",
      "state": "British Columbia",
      "country": "Canada",
      "capacity": 54500,
      "latitude": 49.2768,
      "longitude": -123.1119,
      "timeZone": "America/Vancouver",
      "imageUrl": "assets/worldcup/stadiums/bc_place.jpg",
      "address": "777 Pacific Blvd, Vancouver, BC V6B 4Y8",
      "significance": "Group Stage",
      "matchesHosted": 7,
      "description": "Multi-purpose stadium with retractable roof. Home of BC Lions and Vancouver Whitecaps."
    }
  ]
}
