{
  "playerName": "Kylian Mbappe",
  "fifaCode": "FRA",
  "worldCupAppearances": 14,
  "worldCupGoals": 12,
  "worldCupAssists": 2,
  "previousWorldCups": [2018, 2022],
  "tournamentStats": [
    {
      "year": 2018,
      "matches": 7,
      "goals": 4,
      "assists": 0,
      "stage": "Winner",
      "keyMoment": "Became second teenager after Pel\u00e9 to score in final"
    },
    {
      "year": 2022,
      "matches": 7,
      "goals": 8,
      "assists": 2,
      "stage": "Final",
      "keyMoment": "Hat-trick in final, still lost to Argentina"
    }
  ],
  "worldCupAwards": [
    "World Cup Winner 2018",
    "Golden Boot 2022",
    "Best Young Player 2018",
    "Silver Ball 2022"
  ],
  "memorableMoments": [
    "Hat-trick in 2022 final - only second player after Hurst",
    "Brace vs Argentina in Round of 16 2018",
    "Goal vs Croatia in 2018 World Cup final",
    "12 World Cup goals in just 14 matches"
  ],
  "worldCupLegacyRating": 9,
  "comparisonToLegend": "Already compared to Pel\u00e9 and Thierry Henry for World Cup impact",
  "worldCup2026Prediction": "Will be 27 and entering prime - favorite for Golden Ball"
}
